core/__init__.py
core/config.py
core/models/__init__.py
core/models/dataframe.py
core/models/dataset.py
core/models/dataset_meta.py
dfwriter/__init__.py
dfwriter/abstract_writer.py
dfwriter/csv_writer.py
dfwriter/default_writer.py
dfwriter/dfwriter.py
dfwriter/nc_writer.py
dfwriter/tif_writer.py
parser/__init__.py
parser/abstract_parser.py
parser/csv_parser.py
parser/default_parser.py
parser/dfwriter.py
parser/dir_parser.py
parser/nc_parser.py
parser/tif_parser.py
parser/tiff_arrow_tiff.py
sdk/__init__.py
sdk/connection.py
sdk/connection_pool.py
sdk/dacp_client.py
sdk/dataframe.py
utils/__init__.py
utils/format_utils.py
utils/logger_utils.py
utils/resource_monitoring_info_utils.py
utils/rsa_util.py
utils/sm2_utils.py
faird-1.1.11.dist-info/METADATA
faird-1.1.11.dist-info/WHEEL
faird-1.1.11.dist-info/top_level.txt
faird-1.1.11.dist-info/RECORD
