Metadata-Version: 2.4
Name: faird
Version: 1.1.11
Summary: A SDK for working with DataFrame
Author: rdcn
Author-email: rdcn@cnic.com
Classifier: Programming Language :: Python :: 3
Classifier: License :: OSI Approved :: MIT License
Classifier: Operating System :: OS Independent
Requires-Python: >=3.9
Requires-Dist: pyarrow==19.0.0
Requires-Dist: tabulate
Requires-Dist: pandas
Requires-Dist: netCDF4
Requires-Dist: rasterio
Requires-Dist: requests
Requires-Dist: duckdb
Requires-Dist: pathlib
Dynamic: author
Dynamic: author-email
Dynamic: classifier
Dynamic: requires-dist
Dynamic: requires-python
Dynamic: summary
